setup.cfg
setup.py
systemd_notifier/__init__.py
systemd_notifier/callback.py
systemd_notifier/error.py
systemd_notifier/main.py
systemd_notifier/monitor.py
systemd_notifier/notification.py
systemd_notifier/state.py
systemd_notifier/systemd.py
systemd_notifier.egg-info/PKG-INFO
systemd_notifier.egg-info/SOURCES.txt
systemd_notifier.egg-info/dependency_links.txt
systemd_notifier.egg-info/entry_points.txt
systemd_notifier.egg-info/top_level.txt
systemd_notifier/notifiers/__init__.py
systemd_notifier/notifiers/slack.py