Metadata-Version: 1.1
Name: systemd-notifier
Version: 0.1.1
Summary: Notify for systemd unit status changes
Home-page: http://github.com/drbild/systemd_notifier
Author: David R. Bild
Author-email: david@davidbild.org
License: UNKNOWN
Keywords: systemd monitor alert notify unit slack email status change
Platform: UNKNOWN
Classifier: License :: OSI Approved :: Apache Software License
Classifier: Programming Language :: Python
